ai_hub/__init__.py
ai_hub/globalvar.py
ai_hub/inferServer.py
ai_hub/log.py
ai_hub/logger.py
ai_hub/notice.py
ai_hub/test.py
ai_hub/test_gpu.py
ai_hub/utils.py
ai_hub-0.5.3.dist-info/METADATA
ai_hub-0.5.3.dist-info/WHEEL
ai_hub-0.5.3.dist-info/top_level.txt
ai_hub-0.5.3.dist-info/RECORD
