Metadata-Version: 2.1
Name: ai-hub
Version: 0.5.3
Summary: AI_HUB utils package
Home-page: https://github.com/gaoxiaos/AI_HUB
Author: gaoxiaos
Author-email: ai_hub@qq.com
License: MIT
Platform: UNKNOWN
Classifier: Programming Language :: Python :: 3
Classifier: License :: OSI Approved :: MIT License
Classifier: Operating System :: OS Independent
Requires-Dist: requests (>=1.0.0flask>=1.1.1)
